rolling_ball/__init__.py
rolling_ball/models/__init__.py
rolling_ball/models/alexnet.py
rolling_ball/models/cnn.py
rolling_ball/models/densenet.py
rolling_ball/models/lenet.py
rolling_ball/models/mlp.py
rolling_ball/models/resnet.py
rolling_ball/models/transformer.py
rolling_ball/models/vgg.py
rolling_ball/optim/__init__.py
rolling_ball/optim/entropy_sgd.py
rolling_ball/optim/optax_opts.py
rolling_ball/optim/optim.py
rolling_ball/optim/rbo.py
rolling_ball/optim/sam.py
rolling_ball/utils/__init__.py
rolling_ball/utils/checkpointing.py
rolling_ball/utils/config.py
rolling_ball/utils/data.py
rolling_ball/utils/factory.py
rolling_ball/utils/metrics.py
rolling_ball/utils/spatial.py
rolling_ball/utils/tree.py
rolling_ball-0.0.2.dist-info/METADATA
rolling_ball-0.0.2.dist-info/WHEEL
rolling_ball-0.0.2.dist-info/top_level.txt
rolling_ball-0.0.2.dist-info/RECORD
