Metadata-Version: 2.4
Name: rolling_ball
Version: 0.0.2
Requires-Dist: jax==0.6.2
Requires-Dist: jaxlib==0.6.2
Requires-Dist: flax==0.10.7
Requires-Dist: optax==0.2.5
Requires-Dist: chex==0.1.89
Requires-Dist: grain==0.2.11
Requires-Dist: tensorflow-datasets==4.9.9
Requires-Dist: pydantic==2.11.4
Requires-Dist: albumentations==2.0.8
Requires-Dist: numpy==2.3.1
Requires-Dist: matplotlib==3.10.3
Requires-Dist: pandas==2.2.3
